chrisclient/__init__.py
chrisclient/client.py
chrisclient/exceptions.py
chrisclient/request.py
chrisclient/run.py
chrisclient/search.py
chrisclient/utils.py
python_chrisclient-2.13.0.data/scripts/chrisclient
python_chrisclient-2.13.0.data/scripts/chrispl-run
python_chrisclient-2.13.0.data/scripts/chrispl-search
python_chrisclient-2.13.0.dist-info/LICENSE
python_chrisclient-2.13.0.dist-info/METADATA
python_chrisclient-2.13.0.dist-info/WHEEL
python_chrisclient-2.13.0.dist-info/top_level.txt
python_chrisclient-2.13.0.dist-info/RECORD
