Metadata-Version: 2.2
Name: python-chrisclient
Version: 2.13.0
Summary: (Python) client for the ChRIS API
Home-page: https://github.com/FNNDSC/python-chrisclient
Author: FNNDSC
Author-email: dev@babymri.org
License: MIT
Requires-Python: >=3.8
License-File: LICENSE
Requires-Dist: requests>=2.21.0
Requires-Dist: collection-json>=0.1.1
Requires-Dist: pfstate
Requires-Dist: pfmisc
Requires-Dist: webob
Dynamic: author
Dynamic: author-email
Dynamic: description
Dynamic: home-page
Dynamic: license
Dynamic: requires-dist
Dynamic: requires-python
Dynamic: summary
